flask_wtf/__init__.py
flask_wtf/_compat.py
flask_wtf/csrf.py
flask_wtf/file.py
flask_wtf/form.py
flask_wtf/i18n.py
flask_wtf/recaptcha/__init__.py
flask_wtf/recaptcha/fields.py
flask_wtf/recaptcha/validators.py
flask_wtf/recaptcha/widgets.py
Flask_WTF-1.1.1.dist-info/LICENSE.rst
Flask_WTF-1.1.1.dist-info/METADATA
Flask_WTF-1.1.1.dist-info/WHEEL
Flask_WTF-1.1.1.dist-info/top_level.txt
Flask_WTF-1.1.1.dist-info/RECORD
